sikriml_ner_rule/__init__.py
sikriml_ner_rule/rule_processor.py
sikriml_ner_rule/handlers/__init__.py
sikriml_ner_rule/handlers/account_number_handler.py
sikriml_ner_rule/handlers/card_number_handler.py
sikriml_ner_rule/handlers/number_handler.py
sikriml_ner_rule/handlers/personal_number_handler.py
sikriml_ner_rule/handlers/url_handler.py
sikriml_ner_rule/handlers/word_list_handler.py
sikriml_ner_rule/handlers/year_handler.py
sikriml_ner_rule/handlers/abstracts/__init__.py
sikriml_ner_rule/handlers/abstracts/entity_handler.py
sikriml_ner_rule/handlers/abstracts/regex_handler.py
sikriml_ner_rule/handlers/abstracts/regex_handler_decorator.py
sikriml_ner_rule/models/__init__.py
sikriml_ner_rule/models/card_type.py
sikriml_ner_rule/services/__init__.py
sikriml_ner_rule/services/file_loader.py
sikriml_ner_rule/services/nltk_stemmer.py
sikriml_ner_rule/services/abstracts/__init__.py
sikriml_ner_rule/services/abstracts/data_loader.py
sikriml_ner_rule/services/abstracts/stemmer.py
tests/__init__.py
tests/test_rule_processor.py
tests/handlers/__init__.py
tests/handlers/test_account_number_handler.py
tests/handlers/test_card_number_handler.py
tests/handlers/test_number_handler.py
tests/handlers/test_personal_number_handler.py
tests/handlers/test_url_handler.py
tests/handlers/test_word_list_handler.py
tests/handlers/test_year_handler.py
sikriml_ner_rule-0.1.1b1.dist-info/METADATA
sikriml_ner_rule-0.1.1b1.dist-info/WHEEL
sikriml_ner_rule-0.1.1b1.dist-info/top_level.txt
sikriml_ner_rule-0.1.1b1.dist-info/RECORD
